ncBacktester/__init__.py
ncBacktester/backtest.py
ncBacktester/metrics.py
ncBacktester/plotter.py
ncBacktester/stop_loss.py
ncBacktester/strategy_executor.py
ncbacktester-0.1.1.dist-info/licenses/LICENSE
tests/__init__.py
tests/test_integration.py
tests/test_metrics.py
tests/test_plotter.py
tests/test_stop_loss.py
tests/test_strategy_executor.py
ncbacktester-0.1.1.dist-info/METADATA
ncbacktester-0.1.1.dist-info/WHEEL
ncbacktester-0.1.1.dist-info/top_level.txt
ncbacktester-0.1.1.dist-info/RECORD
