Metadata-Version: 2.4
Name: ncBacktester
Version: 0.1.1
Summary: A simple backtesting engine for trading strategies
Home-page: https://github.com/gjarment/FIM500AlgoTrading
Author: ncBacktester Team
Author-email: sksharm4@ncsu.edu
Project-URL: Bug Reports, https://github.com/gjarment/FIM500AlgoTrading/issues
Project-URL: Source, https://github.com/gjarment/FIM500AlgoTrading/tree/main/ncBacktester
Project-URL: Documentation, https://github.com/gjarment/FIM500AlgoTrading/tree/main/ncBacktester#readme
Keywords: backtesting,trading,finance,strategy,quantitative
Classifier: Development Status :: 3 - Alpha
Classifier: Intended Audience :: Financial and Insurance Industry
Classifier: Intended Audience :: Developers
Classifier: Topic :: Office/Business :: Financial :: Investment
Classifier: License :: OSI Approved :: MIT License
Classifier: Programming Language :: Python :: 3
Classifier: Programming Language :: Python :: 3.8
Classifier: Programming Language :: Python :: 3.9
Classifier: Programming Language :: Python :: 3.10
Classifier: Programming Language :: Python :: 3.11
Requires-Python: >=3.8
License-File: LICENSE
Requires-Dist: pandas>=1.3.0
Requires-Dist: numpy>=1.20.0
Requires-Dist: matplotlib>=3.3.0
Provides-Extra: dev
Requires-Dist: pytest>=7.0.0; extra == "dev"
Requires-Dist: pytest-cov>=3.0.0; extra == "dev"
Requires-Dist: black>=22.0.0; extra == "dev"
Requires-Dist: flake8>=4.0.0; extra == "dev"
Dynamic: author
Dynamic: author-email
Dynamic: classifier
Dynamic: description
Dynamic: description-content-type
Dynamic: home-page
Dynamic: keywords
Dynamic: license-file
Dynamic: project-url
Dynamic: provides-extra
Dynamic: requires-dist
Dynamic: requires-python
Dynamic: summary
